bmgedit/BMGEditing.py
bmgedit/Build.py
bmgedit/__init__.py
bmgedit/best_match_infer/ExtBestHits.py
bmgedit/best_match_infer/Quartets.py
bmgedit/best_match_infer/Scenario.py
bmgedit/best_match_infer/ScenarioFileIO.py
bmgedit/best_match_infer/TreeReconstruction.py
bmgedit/best_match_infer/__init__.py
bmgedit/ilp/CplexBMG.py
bmgedit/ilp/GurobiBMG.py
bmgedit/ilp/__init__.py
bmgedit/partitioning/GreedyBipartition.py
bmgedit/partitioning/Karger.py
bmgedit/partitioning/Louvain.py
bmgedit/partitioning/NumberPartition.py
bmgedit/partitioning/__init__.py
bmgedit-0.0.5.dist-info/LICENSE
bmgedit-0.0.5.dist-info/METADATA
bmgedit-0.0.5.dist-info/WHEEL
bmgedit-0.0.5.dist-info/top_level.txt
bmgedit-0.0.5.dist-info/RECORD
