Metadata-Version: 2.1
Name: bmgedit
Version: 0.0.5
Summary: Best match graph editing.
Home-page: https://github.com/david-schaller/bmg-edit
Author: David Schaller
Author-email: sdavid@bioinf.uni-leipzig.de
Classifier: Programming Language :: Python :: 3
Classifier: License :: OSI Approved :: GNU General Public License v3 (GPLv3)
Classifier: Operating System :: OS Independent
Requires-Python: >=3.7
License-File: LICENSE
Requires-Dist: numpy >=1.16.4
Requires-Dist: scipy >=1.3.0
Requires-Dist: matplotlib >=3.0
Requires-Dist: networkx >=2.2
Requires-Dist: asymmetree >=2.2.0
Requires-Dist: tralda >=1.0.1
